nose_tap/__init__.py
nose_tap/i18n.py
nose_tap/plugin.py
nose_tap/locale/nose_tap.pot
nose_tap/locale/ar/LC_MESSAGES/nose_tap.po
nose_tap/locale/de/LC_MESSAGES/nose_tap.po
nose_tap/locale/es/LC_MESSAGES/nose_tap.po
nose_tap/locale/fr/LC_MESSAGES/nose_tap.po
nose_tap/locale/it/LC_MESSAGES/nose_tap.po
nose_tap/locale/ja/LC_MESSAGES/nose_tap.po
nose_tap/locale/nl/LC_MESSAGES/nose_tap.po
nose_tap/locale/pt/LC_MESSAGES/nose_tap.po
nose_tap/locale/ru/LC_MESSAGES/nose_tap.po
nose_tap/locale/zh/LC_MESSAGES/nose_tap.po
nose_tap/tests/__init__.py
nose_tap/tests/test_plugin.py
nose_tap-3.0.dist-info/LICENSE
nose_tap-3.0.dist-info/METADATA
nose_tap-3.0.dist-info/WHEEL
nose_tap-3.0.dist-info/entry_points.txt
nose_tap-3.0.dist-info/top_level.txt
nose_tap-3.0.dist-info/RECORD
