Metadata-Version: 2.1
Name: nose-tap
Version: 3.0
Summary: Test Anything Protocol (TAP) reporting plugin for nose
Home-page: https://github.com/python-tap/nose-tap
Author: Matt Layman
Author-email: matthewlayman@gmail.com
License: BSD
Keywords: TAP,unittest,nose
Platform: any
Classifier: Development Status :: 5 - Production/Stable
Classifier: Intended Audience :: Developers
Classifier: License :: OSI Approved :: BSD License
Classifier: Operating System :: OS Independent
Classifier: Programming Language :: Python :: 2.7
Classifier: Programming Language :: Python :: 3.5
Classifier: Programming Language :: Python :: 3.6
Classifier: Programming Language :: Python :: 3.7
Classifier: Programming Language :: Python :: Implementation :: PyPy
Classifier: Topic :: Software Development :: Testing
Requires-Dist: nose
Requires-Dist: tap.py
